drivepy/__init__.py
drivepy/main.py
drivepy-1.0.3.dist-info/LICENSE
drivepy-1.0.3.dist-info/METADATA
drivepy-1.0.3.dist-info/WHEEL
drivepy-1.0.3.dist-info/entry_points.txt
drivepy-1.0.3.dist-info/top_level.txt
drivepy-1.0.3.dist-info/RECORD
