Metadata-Version: 2.1
Name: drivepy
Version: 1.0.3
Summary: A tool for managing USB drives and flashing ISOs
Home-page: https://mrfidal.in/cyber-security/DrivePy
Author: Fidal
Author-email: mrfidal@proton.me
License: MIT
Classifier: Programming Language :: Python :: 3
Classifier: License :: OSI Approved :: MIT License
Classifier: Operating System :: OS Independent
Requires-Python: >=3.6
License-File: LICENSE
Requires-Dist: psutil
